contrasttransferfunction/__about__.py
contrasttransferfunction/__init__.py
contrasttransferfunction/contrasttransferfunction.py
contrasttransferfunction/ctffit.py
contrasttransferfunction/frequencyhelper.py
contrasttransferfunction/spectrumhelpers.py
contrasttransferfunction/utils.py
contrasttransferfunction-0.0.1.dist-info/METADATA
contrasttransferfunction-0.0.1.dist-info/WHEEL
contrasttransferfunction-0.0.1.dist-info/licenses/LICENSE.txt
contrasttransferfunction-0.0.1.dist-info/RECORD
