Metadata-Version: 2.1
Name: contrasttransferfunction
Version: 0.0.1
Summary: Tools to model and estimate the contrast transfer function for transmission electron microscopy data
Project-URL: Documentation, https://github.com/unknown/contrasttransferfunction#readme
Project-URL: Issues, https://github.com/unknown/contrasttransferfunction/issues
Project-URL: Source, https://github.com/unknown/contrasttransferfunction
Author-email: Johannes Elferich <jojotux123@hotmail.com>
License-Expression: MIT
License-File: LICENSE.txt
Classifier: Development Status :: 4 - Beta
Classifier: Programming Language :: Python
Classifier: Programming Language :: Python :: 3.7
Classifier: Programming Language :: Python :: 3.8
Classifier: Programming Language :: Python :: 3.9
Classifier: Programming Language :: Python :: 3.10
Classifier: Programming Language :: Python :: 3.11
Classifier: Programming Language :: Python :: Implementation :: CPython
Classifier: Programming Language :: Python :: Implementation :: PyPy
Requires-Python: >=3.7
Requires-Dist: numpy
Requires-Dist: pydantic
Requires-Dist: scipy
